vrcosc/__init__.py
vrcosc-0.2.0.dist-info/METADATA
vrcosc-0.2.0.dist-info/WHEEL
vrcosc-0.2.0.dist-info/licenses/LICENSE
vrcosc-0.2.0.dist-info/RECORD
