Metadata-Version: 2.4
Name: vrcosc
Version: 0.2.0
Summary: A project that aims to simplify OSC communication to VRChat in Python.
Project-URL: Homepage, https://github.com/ItzuCrafty/VRCOSC
Project-URL: Issues, https://github.com/ItzuCrafty/VRCOSC/issues
Author: ItzuCrafty
License: GPL-3.0-only
License-File: LICENSE
Keywords: osc,vrchat
Classifier: License :: OSI Approved :: GNU General Public License v3 (GPLv3)
Classifier: Operating System :: OS Independent
Classifier: Programming Language :: Python :: 3.12
Requires-Python: ==3.12.*
Requires-Dist: python-osc>=1.9.3
